pyvndbhttp.py
pyvndbhttp-0.1.1.dist-info/LICENSE
pyvndbhttp-0.1.1.dist-info/WHEEL
pyvndbhttp-0.1.1.dist-info/METADATA
pyvndbhttp-0.1.1.dist-info/RECORD
